scalecol/__init__.py
scalecol-0.1.dist-info/METADATA
scalecol-0.1.dist-info/WHEEL
scalecol-0.1.dist-info/top_level.txt
scalecol-0.1.dist-info/RECORD
